tfs_viewer/__init__.py
tfs_viewer/app.py
tfs_viewer/displays.py
tfs_viewer/figures.py
tfs_viewer/forms.py
tfs_viewer/upload.py
tfs_viewer-0.2.1.dist-info/METADATA
tfs_viewer-0.2.1.dist-info/WHEEL
tfs_viewer-0.2.1.dist-info/licenses/LICENSE
tfs_viewer-0.2.1.dist-info/RECORD
