Metadata-Version: 2.3
Name: tfs_viewer
Version: 0.2.1
Summary: A Streamlit application to explore data in TFS files.
Project-URL: homepage, https://github.com/fsoubelet/streamlit_tfs_viewer
Project-URL: repository, https://github.com/fsoubelet/streamlit_tfs_viewer
Author-email: Felix Soubelet <felix.soubelet@cern.ch>
License-Expression: MIT
License-File: LICENSE
Classifier: Development Status :: 4 - Beta
Classifier: License :: OSI Approved :: MIT License
Classifier: Natural Language :: English
Classifier: Operating System :: OS Independent
Classifier: Programming Language :: Python :: 3 :: Only
Classifier: Programming Language :: Python :: 3.9
Classifier: Programming Language :: Python :: 3.10
Classifier: Programming Language :: Python :: 3.11
Classifier: Programming Language :: Python :: 3.12
Classifier: Programming Language :: Python :: Implementation :: CPython
Classifier: Topic :: Software Development :: Libraries :: Python Modules
Classifier: Typing :: Typed
Requires-Python: >=3.9
Requires-Dist: matplotlib>=3.8
Requires-Dist: plotly>=5.15
Requires-Dist: streamlit>=1.30
Requires-Dist: tfs-pandas>=3.8
Requires-Dist: watchdog>=4.0
